keysigner/__init__.py
keysigner/apk_signer.py
keysigner/keystore_generator.py
keysigner/keystore_info.py
keysigner/keystore_migrator.py
keysigner/main.py
keysigner/pem_to_pkcs12.py
keysigner/pkcs12_to_pem.py
keysigner/utils.py
keysigner/lib/bcprov-jdk18on-1.78.jar
keysigner/lib/testkey.pk8
keysigner/lib/testkey.x509.pem
keysigner-4.0.dist-info/LICENSE
keysigner-4.0.dist-info/METADATA
keysigner-4.0.dist-info/WHEEL
keysigner-4.0.dist-info/entry_points.txt
keysigner-4.0.dist-info/top_level.txt
keysigner-4.0.dist-info/RECORD
