Metadata-Version: 2.1
Name: keysigner
Version: 4.0
Summary: A command-line tool for keystore management and APK signing for Android developers.
Author-email: MuhammadRizwan <mrizwan87@protonmail.com>
License: MIT License
Project-URL: homepage, https://github.com/muhammadrizwan87/keysigner
Classifier: Programming Language :: Python
Classifier: Programming Language :: Python :: 3
Classifier: License :: OSI Approved :: MIT License
Classifier: Operating System :: OS Independent
License-File: LICENSE
